{
  "url": "https://developers.figma.com/docs/plugins/api/properties/nodes-manualkeyframetracks/",
  "path": "/docs/plugins/api/properties/nodes-manualkeyframetracks/",
  "slug": "docs__plugins__api__properties__nodes-manualkeyframetracks",
  "title": "manualKeyframeTracks | Developer Docs",
  "markdown": "*   [](/)\n*   Plugins\n*   [Shared Node Properties](/docs/plugins/api/node-properties/)\n*   manualKeyframeTracks\n\n# manualKeyframeTracks\n\nThe manual Motion keyframe tracks bound to this node.\n\nSupported on:\n\n*   [BooleanOperationNode](/docs/plugins/api/BooleanOperationNode/)\n*   [CodeBlockNode](/docs/plugins/api/CodeBlockNode/)\n*   [ComponentNode](/docs/plugins/api/ComponentNode/)\n*   [ComponentSetNode](/docs/plugins/api/ComponentSetNode/)\n*   [ConnectorNode](/docs/plugins/api/ConnectorNode/)\n*   [EllipseNode](/docs/plugins/api/EllipseNode/)\n*   [EmbedNode](/docs/plugins/api/EmbedNode/)\n*   [FrameNode](/docs/plugins/api/FrameNode/)\n*   [GroupNode](/docs/plugins/api/GroupNode/)\n*   [HighlightNode](/docs/plugins/api/HighlightNode/)\n*   [InstanceNode](/docs/plugins/api/InstanceNode/)\n*   [InteractiveSlideElementNode](/docs/plugins/api/InteractiveSlideElementNode/)\n*   [LineNode](/docs/plugins/api/LineNode/)\n*   [LinkUnfurlNode](/docs/plugins/api/LinkUnfurlNode/)\n*   [MediaNode](/docs/plugins/api/MediaNode/)\n*   [PolygonNode](/docs/plugins/api/PolygonNode/)\n*   [RectangleNode](/docs/plugins/api/RectangleNode/)\n*   [SectionNode](/docs/plugins/api/SectionNode/)\n*   [ShapeWithTextNode](/docs/plugins/api/ShapeWithTextNode/)\n*   [SliceNode](/docs/plugins/api/SliceNode/)\n*   [SlideGridNode](/docs/plugins/api/SlideGridNode/)\n*   [SlideNode](/docs/plugins/api/SlideNode/)\n*   [SlideRowNode](/docs/plugins/api/SlideRowNode/)\n*   [SlotNode](/docs/plugins/api/SlotNode/)\n*   [StampNode](/docs/plugins/api/StampNode/)\n*   [StarNode](/docs/plugins/api/StarNode/)\n*   [StickyNode](/docs/plugins/api/StickyNode/)\n*   [TableNode](/docs/plugins/api/TableNode/)\n*   [TextNode](/docs/plugins/api/TextNode/)\n*   [TextPathNode](/docs/plugins/api/TextPathNode/)\n*   [TransformGroupNode](/docs/plugins/api/TransformGroupNode/)\n*   [VectorNode](/docs/plugins/api/VectorNode/)\n*   [WashiTapeNode](/docs/plugins/api/WashiTapeNode/)\n*   [WidgetNode](/docs/plugins/api/WidgetNode/)\n\n## Signature​\n\n### [manualKeyframeTracks](/docs/plugins/api/properties/nodes-manualkeyframetracks/): [ManualKeyframeTracks](/docs/plugins/api/Motion/#manual-keyframe-tracks) \\[readonly\\]\n\n## Remarks​\n\n```\nconst node = figma.currentPage.selection[0]const manualTranslationX = node?.manualKeyframeTracks.TRANSLATION_Xif (manualTranslationX) {  console.log(manualTranslationX.keyframes)}\n```\n\n[\n\nPrevious\n\nlocked\n\n](/docs/plugins/api/properties/nodes-locked/)[\n\nNext\n\nname\n\n](/docs/plugins/api/properties/nodes-name/)\n\n*   Signature\n*   Remarks"
}