{
  "url": "https://developers.figma.com/docs/plugins/api/properties/nodes-strokecap/",
  "path": "/docs/plugins/api/properties/nodes-strokecap/",
  "slug": "docs__plugins__api__properties__nodes-strokecap",
  "title": "strokeCap | Developer Docs",
  "markdown": "*   [](/)\n*   Plugins\n*   [Shared Node Properties](/docs/plugins/api/node-properties/)\n*   strokeCap\n\n# strokeCap\n\nThe decoration applied to vertices which have only one connected segment.\n\nSupported on:\n\n*   [BooleanOperationNode](/docs/plugins/api/BooleanOperationNode/)\n*   [ComponentNode](/docs/plugins/api/ComponentNode/)\n*   [ComponentSetNode](/docs/plugins/api/ComponentSetNode/)\n*   [EllipseNode](/docs/plugins/api/EllipseNode/)\n*   [FrameNode](/docs/plugins/api/FrameNode/)\n*   [HighlightNode](/docs/plugins/api/HighlightNode/)\n*   [InstanceNode](/docs/plugins/api/InstanceNode/)\n*   [LineNode](/docs/plugins/api/LineNode/)\n*   [PolygonNode](/docs/plugins/api/PolygonNode/)\n*   [RectangleNode](/docs/plugins/api/RectangleNode/)\n*   [SlideNode](/docs/plugins/api/SlideNode/)\n*   [SlotNode](/docs/plugins/api/SlotNode/)\n*   [StampNode](/docs/plugins/api/StampNode/)\n*   [StarNode](/docs/plugins/api/StarNode/)\n*   [TextNode](/docs/plugins/api/TextNode/)\n*   [TextPathNode](/docs/plugins/api/TextPathNode/)\n*   [VectorNode](/docs/plugins/api/VectorNode/)\n*   [WashiTapeNode](/docs/plugins/api/WashiTapeNode/)\n\n## Signature​\n\n### [strokeCap](/docs/plugins/api/properties/nodes-strokecap/): [StrokeCap](/docs/plugins/api/StrokeCap/) | [figma.mixed](/docs/plugins/api/properties/figma-mixed/)\n\n## Remarks​\n\nOn a vector network, the value is set on the whole vector network. Use the vector network API to set it on individual vertices.\n\nThis property can return [`figma.mixed`](/docs/plugins/api/properties/figma-mixed/) if different vertices have different values.properties.\n\n[\n\nPrevious\n\nstrokeAlign\n\n](/docs/plugins/api/properties/nodes-strokealign/)[\n\nNext\n\nstrokeJoin\n\n](/docs/plugins/api/properties/nodes-strokejoin/)\n\n*   Signature\n*   Remarks"
}