{
  "url": "https://developers.figma.com/docs/plugins/api/TextSublayer/",
  "path": "/docs/plugins/api/TextSublayer/",
  "slug": "docs__plugins__api__TextSublayer",
  "title": "TextSublayer | Developer Docs",
  "markdown": "*   [](/)\n*   Plugins\n*   [Data Types](/docs/plugins/api/data-types/)\n*   TextSublayer\n\n# TextSublayer\n\nText sublayer nodes are pared-back versions of text nodes: they have most text properties (except `textAlignVertical` and `textAutoResize`, which are not editable on these nodes' text sublayers), as well as `fills`. They aren't resizable or repositionable.\n\nYou set text content as you would for any other text node (e.g. `sticky.text.characters = 'some text'`). As with all other text operations in Figma, you'll need to ensure [fonts are loaded](/docs/plugins/working-with-text/#loading-fonts).\n\n## Basic traits​\n\n### [toString](/docs/plugins/api/properties/nodes-tostring/)(): string\n\nReturns a string representation of the node. For debugging purposes only, do not rely on the exact output of this string in production code.\n\n[View more →](/docs/plugins/api/properties/nodes-tostring/)\n\n* * *\n\n### [parent](/docs/plugins/api/properties/nodes-parent/): ([BaseNode](/docs/plugins/api/nodes/#base-node) & [ChildrenMixin](/docs/plugins/api/node-properties/#children-mixin)) | null \\[readonly\\]\n\nReturns the parent of this node, if any. This property is not meant to be directly edited. To reparent, see [`appendChild`](/docs/plugins/api/properties/nodes-appendchild/).\n\n[View more →](/docs/plugins/api/properties/nodes-parent/)\n\n* * *\n\ntip\n\nTip: `parent` will always return a [ConnectorNode](/docs/plugins/api/ConnectorNode/), [ShapeWithTextNode](/docs/plugins/api/ShapeWithTextNode/), [StickyNode](/docs/plugins/api/StickyNode/), or [TableCellNode](/docs/plugins/api/TableCellNode/)\n\n## Text node traits​\n\n### paragraphIndent: number\n\nThe indentation of paragraphs (offset of the first line from the left). Setting this property requires the font the be loaded.\n\n* * *\n\n### paragraphSpacing: number\n\nThe vertical distance between paragraphs. Setting this property requires the font to be loaded.\n\n* * *\n\n### listSpacing: number\n\nThe vertical distance between lines of a list.\n\n* * *\n\n### hangingPunctuation: boolean\n\nWhether punctuation, like quotation marks, hangs outside the text box.\n\n* * *\n\n### hangingList: boolean\n\nWhether numbered list counters or unordered list bullets hang outside the text box.\n\n* * *\n\n### textDecoration: [TextDecoration](/docs/plugins/api/TextDecoration/) | [figma.mixed](/docs/plugins/api/properties/figma-mixed/)\n\nWhether the text is underlined or has a strikethrough. Requires the font to be loaded.\n\n* * *\n\n### textDecorationStyle: [TextDecorationStyle](/docs/plugins/api/TextDecorationStyle/) | [figma.mixed](/docs/plugins/api/properties/figma-mixed/) | null\n\nThe text decoration style (e.g. \"SOLID\"). If the text is not underlined, this value will be null. Requires the font to be loaded.\n\n* * *\n\n### textDecorationOffset: [TextDecorationOffset](/docs/plugins/api/TextDecorationOffset/) | [figma.mixed](/docs/plugins/api/properties/figma-mixed/) | null\n\nThe text decoration offset. If the text is not underlined, this value will be null. Requires the font to be loaded.\n\n* * *\n\n### textDecorationThickness: [TextDecorationThickness](/docs/plugins/api/TextDecorationThickness/) | [figma.mixed](/docs/plugins/api/properties/figma-mixed/) | null\n\nThe text decoration thickness. If the text is not underlined, this value will be null. Requires the font to be loaded.\n\n* * *\n\n### textDecorationColor: [TextDecorationColor](/docs/plugins/api/TextDecorationColor/) | [figma.mixed](/docs/plugins/api/properties/figma-mixed/) | null\n\nThe text decoration color. If the text is not underlined, this value will be null. Requires the font to be loaded.\n\n* * *\n\n### textDecorationSkipInk: boolean | [figma.mixed](/docs/plugins/api/properties/figma-mixed/) | null\n\nWhether the text decoration skips descenders. If the text is not underlined, this value will be null. Requires the font to be loaded.\n\n* * *\n\n### lineHeight: [LineHeight](/docs/plugins/api/LineHeight/) | [figma.mixed](/docs/plugins/api/properties/figma-mixed/)\n\nThe spacing between the lines in a paragraph of text. Requires the font to be loaded.\n\n* * *\n\n### leadingTrim: [LeadingTrim](/docs/plugins/api/LeadingTrim/) | [figma.mixed](/docs/plugins/api/properties/figma-mixed/)\n\nThe removal of the vertical space above and below text glyphs. Requires the font to be loaded.\n\n* * *\n\n### getRangeTextDecoration(start: number, end: number): [TextDecoration](/docs/plugins/api/TextDecoration/) | [figma.mixed](/docs/plugins/api/properties/figma-mixed/)\n\nGet the `textDecoration` from characters in range `start` (inclusive) to `end` (exclusive).\n\n* * *\n\n### setRangeTextDecoration(start: number, end: number, value: [TextDecoration](/docs/plugins/api/TextDecoration/)): void\n\nSet the `textDecoration` from characters in range `start` (inclusive) to `end` (exclusive). Requires the font to be loaded.\n\n* * *\n\n### getRangeTextDecorationStyle(start: number, end: number): [TextDecorationStyle](/docs/plugins/api/TextDecorationStyle/) | [figma.mixed](/docs/plugins/api/properties/figma-mixed/) | null\n\nGet the `textDecorationStyle` from characters in range `start` (inclusive) to `end` (exclusive).\n\n* * *\n\n### setRangeTextDecorationStyle(start: number, end: number, value: [TextDecorationStyle](/docs/plugins/api/TextDecorationStyle/)): void\n\nSet the `textDecorationStyle` from characters in range `start` (inclusive) to `end` (exclusive). Requires the font to be loaded.\n\n* * *\n\n### getRangeTextDecorationOffset(start: number, end: number): [TextDecorationOffset](/docs/plugins/api/TextDecorationOffset/) | [figma.mixed](/docs/plugins/api/properties/figma-mixed/) | null\n\nGet the `textDecorationOffset` from characters in range `start` (inclusive) to `end` (exclusive).\n\n* * *\n\n### setRangeTextDecorationOffset(start: number, end: number, value: [TextDecorationOffset](/docs/plugins/api/TextDecorationOffset/)): void\n\nSet the `textDecorationOffset` from characters in range `start` (inclusive) to `end` (exclusive). Requires the font to be loaded.\n\n* * *\n\n### getRangeTextDecorationThickness(start: number, end: number): [TextDecorationThickness](/docs/plugins/api/TextDecorationThickness/) | [figma.mixed](/docs/plugins/api/properties/figma-mixed/) | null\n\nGet the `textDecorationThickness` from characters in range `start` (inclusive) to `end` (exclusive).\n\n* * *\n\n### setRangeTextDecorationThickness(start: number, end: number, value: [TextDecorationThickness](/docs/plugins/api/TextDecorationThickness/)): void\n\nSet the `textDecorationThickness` from characters in range `start` (inclusive) to `end` (exclusive). Requires the font to be loaded.\n\n* * *\n\n### getRangeTextDecorationColor(start: number, end: number): [TextDecorationColor](/docs/plugins/api/TextDecorationColor/) | [figma.mixed](/docs/plugins/api/properties/figma-mixed/) | null\n\nGet the `textDecorationColor` from characters in range `start` (inclusive) to `end` (exclusive).\n\n* * *\n\n### setRangeTextDecorationColor(start: number, end: number, value: [TextDecorationColor](/docs/plugins/api/TextDecorationColor/)): void\n\nSet the `textDecorationColor` from characters in range `start` (inclusive) to `end` (exclusive). Requires the font to be loaded.\n\n* * *\n\n### getRangeTextDecorationSkipInk(start: number, end: number): boolean | [figma.mixed](/docs/plugins/api/properties/figma-mixed/) | null\n\nGet the `textDecorationSkipInk` from characters in range `start` (inclusive) to `end` (exclusive).\n\n* * *\n\n### setRangeTextDecorationSkipInk(start: number, end: number, value: boolean): void\n\nSet the `textDecorationSkipInk` from characters in range `start` (inclusive) to `end` (exclusive). Requires the font to be loaded.\n\n* * *\n\n### getRangeLineHeight(start: number, end: number): [LineHeight](/docs/plugins/api/LineHeight/) | [figma.mixed](/docs/plugins/api/properties/figma-mixed/)\n\nGet the `lineHeight` from characters in range `start` (inclusive) to `end` (exclusive).\n\n* * *\n\n### setRangeLineHeight(start: number, end: number, value: [LineHeight](/docs/plugins/api/LineHeight/)): void\n\nSet the `lineHeight` from characters in range `start` (inclusive) to `end` (exclusive). Requires the font to be loaded.\n\n* * *\n\n### getRangeListOptions(start: number, end: number): [TextListOptions](/docs/plugins/api/TextListOptions/) | [figma.mixed](/docs/plugins/api/properties/figma-mixed/)\n\nGet the `textListOptions` from characters in range `start` (inclusive) to `end` (exclusive). Returns a [`TextListOptions`](/docs/plugins/api/TextListOptions/)\n\n* * *\n\n### setRangeListOptions(start: number, end: number, value: [TextListOptions](/docs/plugins/api/TextListOptions/)): void\n\nSet the `textListOptions` from characters in range `start` (inclusive) to `end` (exclusive).\n\n* * *\n\n### getRangeListSpacing(start: number, end: number): number | [figma.mixed](/docs/plugins/api/properties/figma-mixed/)\n\nGet the `listSpacing` from characters in range `start` (inclusive) to `end` (exclusive).\n\n* * *\n\n### setRangeListSpacing(start: number, end: number, value: number): void\n\nSet the `listSpacing` from characters in range `start` (inclusive) to `end` (exclusive).\n\n* * *\n\n### getRangeIndentation(start: number, end: number): number | [figma.mixed](/docs/plugins/api/properties/figma-mixed/)\n\nGet the `indentation` from characters in range `start` (inclusive) to `end` (exclusive).\n\n* * *\n\n### setRangeIndentation(start: number, end: number, value: number): void\n\nSet the `indentation` from characters in range `start` (inclusive) to `end` (exclusive).\n\n* * *\n\n### getRangeParagraphIndent(start: number, end: number): number | [figma.mixed](/docs/plugins/api/properties/figma-mixed/)\n\nGet the `paragraphIndent` for a paragraph containing characters in range `start` (inclusive) to `end` (exclusive).\n\n* * *\n\n### setRangeParagraphIndent(start: number, end: number, value: number): void\n\nSet the `paragraphIndent` for a paragraph containing characters in range `start` (inclusive) to `end` (exclusive).\n\n* * *\n\n### getRangeParagraphSpacing(start: number, end: number): number | [figma.mixed](/docs/plugins/api/properties/figma-mixed/)\n\nGet the `paragraphSpacing` for a paragraph containing characters in range `start` (inclusive) to `end` (exclusive).\n\n* * *\n\n### setRangeParagraphSpacing(start: number, end: number, value: number): void\n\nSet the `paragraphSpacing` for a paragraph containing characters in range `start` (inclusive) to `end` (exclusive).\n\n* * *\n\n### [fills](/docs/plugins/api/properties/nodes-fills/): ReadonlyArray<[Paint](/docs/plugins/api/Paint/)\\> | [figma.mixed](/docs/plugins/api/properties/figma-mixed/)\n\nThe paints used to fill the area of the shape. For help on how to change this value, see [Editing Properties](/docs/plugins/editing-properties/).\n\n[View more →](/docs/plugins/api/properties/nodes-fills/)\n\n* * *\n\n### [fillStyleId](/docs/plugins/api/properties/nodes-fillstyleid/): string | [figma.mixed](/docs/plugins/api/properties/figma-mixed/)\n\nThe id of the [`PaintStyle`](/docs/plugins/api/PaintStyle/) object that the [`fills`](/docs/plugins/api/properties/nodes-fills/) property of this node is linked to.\n\nIf the manifest contains`\"documentAccess\": \"dynamic-page\"`, this property is read-only. Use `setFillStyleIdAsync` to update the style.\n\n[View more →](/docs/plugins/api/properties/nodes-fillstyleid/)\n\n* * *\n\n### setFillStyleIdAsync(styleId: string): Promise<void>\n\nSets the [`PaintStyle`](/docs/plugins/api/PaintStyle/) that the [`fills`](/docs/plugins/api/properties/nodes-fills/) property of this node is linked to.\n\n* * *\n\n### setFillsAsync(paints: ReadonlyArray<[Paint](/docs/plugins/api/Paint/)\\>): Promise<void>\n\nSets the fills of the node asynchronously. This is the only way to set pattern fills on a node, since we need to ensure that the source node of the pattern is loaded first. See [Adding Pattern Fills and Strokes](/docs/plugins/adding-pattern-fills-and-strokes/) for more information.\n\n* * *\n\n[\n\nPrevious\n\nTextStyleOverrides\n\n](/docs/plugins/api/TextStyleOverrides/)[\n\nNext\n\nTransition\n\n](/docs/plugins/api/Transition/)\n\n*   Basic traits\n*   Text node traits"
}