{
  "url": "https://developers.figma.com/docs/plugins/api/properties/figma-createlinkpreviewasync/",
  "path": "/docs/plugins/api/properties/figma-createlinkpreviewasync/",
  "slug": "docs__plugins__api__properties__figma-createlinkpreviewasync",
  "title": "createLinkPreviewAsync | Developer Docs",
  "markdown": "*   [](/)\n*   Plugins\n*   [Global Objects](/docs/plugins/api/global-objects/)\n*   [figma](/docs/plugins/api/figma/)\n*   createLinkPreviewAsync\n\n# createLinkPreviewAsync\n\ninfo\n\nThis API is only available in FigJam.\n\nResolves link metadata from a URL, and inserts either an embed or a unfurled preview of the link into the document An embed will be inserted if the URL is a valid OEmbed provider (has a `<link type=\"application/json+oembed\" ... />` tag). The returned `<iframe>` source will be converted into an EmbedNode.\n\nOtherwise, the title, description, thumbnail, and favicon will be parsed from the HTML markup of the URL using standard `og` or `twitter` meta tags. This information will be converted into a LinkUnfurlNode.\n\n## Signature​\n\n### [createLinkPreviewAsync](/docs/plugins/api/properties/figma-createlinkpreviewasync/)(url: string): Promise<[EmbedNode](/docs/plugins/api/EmbedNode/) | [LinkUnfurlNode](/docs/plugins/api/LinkUnfurlNode/)\\>\n\n## Parameters​\n\n### url​\n\n## Remarks​\n\nThis API is only available in FigJam\n\nCreating embeds and link unfurl nodes\n\n```\n(async () => {  // Creates an EmbedNode  const youtubeEmbed = await figma.createLinkPreviewAsync('https://www.youtube.com/watch?v=4G9RHt2OyuY')  // Creates a LinkUnfurlNode  const unfurledLink = await figma.createLinkPreviewAsync('https://www.figma.com/community/plugins')})()\n```\n\n[\n\nPrevious\n\ncreateVideoAsync\n\n](/docs/plugins/api/properties/figma-createvideoasync/)[\n\nNext\n\ncreateGif\n\n](/docs/plugins/api/properties/figma-creategif/)\n\n*   Signature\n*   Parameters\n    *   url\n*   Remarks"
}